clipy_hooks/__init__.py
clipy_hooks/cli.py
clipy_hooks-0.2.2.dist-info/LICENSE
clipy_hooks-0.2.2.dist-info/METADATA
clipy_hooks-0.2.2.dist-info/WHEEL
clipy_hooks-0.2.2.dist-info/top_level.txt
clipy_hooks-0.2.2.dist-info/RECORD
