Metadata-Version: 2.1
Name: clipy-hooks
Version: 0.2.2
Summary: Convert CLI tools into pre-commit hooks using python.
Home-page: https://github.com/CreatingNull/clipy-hooks
Author: Steve Richardson
Author-email: steve.public@nulltek.xyz
License: Apache2
Classifier: License :: OSI Approved :: Apache Software License
Classifier: Programming Language :: Python :: 3
Classifier: Programming Language :: Python :: 3 :: Only
Classifier: Programming Language :: Python :: 3.8
Classifier: Programming Language :: Python :: 3.9
Classifier: Programming Language :: Python :: 3.10
Classifier: Programming Language :: Python :: 3.11
Classifier: Programming Language :: Python :: 3.12
Requires-Python: >=3.8
License-File: LICENSE
